odoo/addons/maintenance_plan/README.rst
odoo/addons/maintenance_plan/__init__.py
odoo/addons/maintenance_plan/__manifest__.py
odoo/addons/maintenance_plan/hooks.py
odoo/addons/maintenance_plan/data/demo_maintenance_plan.xml
odoo/addons/maintenance_plan/i18n/es.po
odoo/addons/maintenance_plan/i18n/it.po
odoo/addons/maintenance_plan/i18n/maintenance_plan.pot
odoo/addons/maintenance_plan/i18n/zh_CN.po
odoo/addons/maintenance_plan/migrations/13.0.1.2.0/post-migration.py
odoo/addons/maintenance_plan/migrations/13.0.1.2.4/noupdate_changes.xml
odoo/addons/maintenance_plan/migrations/13.0.1.2.4/post-migration.py
odoo/addons/maintenance_plan/models/__init__.py
odoo/addons/maintenance_plan/models/maintenance.py
odoo/addons/maintenance_plan/models/maintenance_equipment.py
odoo/addons/maintenance_plan/models/maintenance_kind.py
odoo/addons/maintenance_plan/models/maintenance_plan.py
odoo/addons/maintenance_plan/models/maintenance_request.py
odoo/addons/maintenance_plan/readme/CONTRIBUTORS.rst
odoo/addons/maintenance_plan/readme/DESCRIPTION.rst
odoo/addons/maintenance_plan/readme/INSTALL.rst
odoo/addons/maintenance_plan/readme/USAGE.rst
odoo/addons/maintenance_plan/security/ir.model.access.csv
odoo/addons/maintenance_plan/security/maintenance_security.xml
odoo/addons/maintenance_plan/static/description/icon.png
odoo/addons/maintenance_plan/static/description/index.html
odoo/addons/maintenance_plan/tests/__init__.py
odoo/addons/maintenance_plan/tests/common.py
odoo/addons/maintenance_plan/tests/test_maintenance_plan.py
odoo/addons/maintenance_plan/views/maintenance_equipment_views.xml
odoo/addons/maintenance_plan/views/maintenance_kind_views.xml
odoo/addons/maintenance_plan/views/maintenance_plan_views.xml
odoo/addons/maintenance_plan/views/report_maintenance_request.xml
odoo13_addon_maintenance_plan-13.0.1.9.0.dist-info/METADATA
odoo13_addon_maintenance_plan-13.0.1.9.0.dist-info/WHEEL
odoo13_addon_maintenance_plan-13.0.1.9.0.dist-info/top_level.txt
odoo13_addon_maintenance_plan-13.0.1.9.0.dist-info/RECORD
