Metadata-Version: 2.1
Name: odoo13-addon-maintenance-plan
Version: 13.0.1.9.0
Summary: Extends preventive maintenance planning
Home-page: https://github.com/OCA/maintenance
Author: Camptocamp SA, ForgeFlow, Odoo Community Association (OCA)
Author-email: support@odoo-community.org
License: AGPL-3
Platform: UNKNOWN
Classifier: Programming Language :: Python
Classifier: Framework :: Odoo
Classifier: Framework :: Odoo :: 13.0
Classifier: License :: OSI Approved :: GNU Affero General Public License v3
Requires-Python: >=3.5
Requires-Dist: odoo13-addon-base-maintenance
Requires-Dist: odoo (<13.1dev,>=13.0a)
Requires-Dist: python-dateutil
